mappable/__init__.py
mappable/__main__.py
mappable/map.py
mappable/server.py
mappable/version.py
mappable/static/asset-manifest.json
mappable/static/favicon.ico
mappable/static/index.html
mappable/static/precache-manifest.3e4c876712f8d03d231646fcc22e6a2e.js
mappable/static/service-worker.js
mappable/static/static/css/2.9ab5f595.chunk.css
mappable/static/static/css/2.9ab5f595.chunk.css.map
mappable/static/static/js/2.5746f700.chunk.js
mappable/static/static/js/2.5746f700.chunk.js.LICENSE.txt
mappable/static/static/js/2.5746f700.chunk.js.map
mappable/static/static/js/main.9b2bebee.chunk.js
mappable/static/static/js/main.9b2bebee.chunk.js.map
mappable/static/static/js/runtime-main.8082a0d0.js
mappable/static/static/js/runtime-main.8082a0d0.js.map
mappable/static/static/media/logo.2794b2ba.svg
test/__init__.py
test/test_mappable_dataset.py
mappable-0.1.2.dist-info/METADATA
mappable-0.1.2.dist-info/WHEEL
mappable-0.1.2.dist-info/entry_points.txt
mappable-0.1.2.dist-info/top_level.txt
mappable-0.1.2.dist-info/RECORD
