Metadata-Version: 2.1
Name: mappable
Version: 0.1.2
Summary: An interactive data annotation tool.
Home-page: https://mappable.ai/
Author: Mark Neumann
Author-email: mark.neumann.1992@gmail.com
License: Unlicensed
Keywords: annotation data text machine learning
Platform: UNKNOWN
Classifier: Intended Audience :: Science/Research
Classifier: Programming Language :: Python :: 3.6
Classifier: Topic :: Scientific/Engineering :: Artificial Intelligence
Requires-Python: >=3.6.0
Requires-Dist: pandas
Requires-Dist: fastapi
Requires-Dist: uvicorn
Requires-Dist: aiofiles
Requires-Dist: numpy
Requires-Dist: typer
Requires-Dist: sqlite-utils
